algosinpy/__init__.py
algosinpy/algorithm/__init__.py
algosinpy/algorithm/data_structures/__init__.py
algosinpy/algorithm/data_structures/queue.py
algosinpy/algorithm/data_structures/topological_sort.py
algosinpy/algorithm/dynamic_programming/__init__.py
algosinpy/algorithm/dynamic_programming/longest_common_subsequence.py
algosinpy/algorithm/dynamic_programming/longest_increasing_subsequence.py
algosinpy/algorithm/graphs/__init__.py
algosinpy/algorithm/graphs/breadth_first_search.py
algosinpy/algorithm/graphs/depth_first_search.py
algosinpy/algorithm/searching/__init__.py
algosinpy/algorithm/searching/binary_search.py
algosinpy/algorithm/sorting/__init__.py
algosinpy/algorithm/sorting/sorting.py
algosinpy/algorithm/tree/__init__.py
algosinpy/algorithm/tree/binary_indexed_tree.py
algosinpy/algorithm/tree/segment_tree.py
algosinpy/logger/__init__.py
algosinpy/logger/py_logger.py
algosinpy/test/__init__.py
algosinpy/test/algorithm/__init__.py
algosinpy/test/algorithm/data_structures/__init__.py
algosinpy/test/algorithm/data_structures/test_queue.py
algosinpy/test/algorithm/dynamic_programming/__init__.py
algosinpy/test/algorithm/dynamic_programming/test_longest_common_subsequence.py
algosinpy/test/algorithm/dynamic_programming/test_longest_increasing_subsequence.py
algosinpy/test/algorithm/graphs/__init__.py
algosinpy/test/algorithm/graphs/test_breadth_first_search.py
algosinpy/test/algorithm/graphs/test_depth_first_search.py
algosinpy/test/algorithm/searching/__init__.py
algosinpy/test/algorithm/searching/test_binary_search.py
algosinpy/test/algorithm/sorting/__init__.py
algosinpy/test/algorithm/sorting/sorting_test.py
algosinpy/test/algorithm/tree/__init__.py
algosinpy/test/algorithm/tree/test_binary_indexed_tree.py
algosinpy/test/algorithm/tree/test_segment_tree.py
algosinpy-0.1.0.dist-info/licenses/LICENSE
algosinpy-0.1.0.dist-info/METADATA
algosinpy-0.1.0.dist-info/WHEEL
algosinpy-0.1.0.dist-info/top_level.txt
algosinpy-0.1.0.dist-info/RECORD
