Metadata-Version: 2.4
Name: algosinpy
Version: 0.1.0
Summary: Python implementation of data structures and algorithms
Author-email: Mobarak Hose Shakil <mh.ice.iu@gmail.com>
License: MIT
Project-URL: Homepage, https://github.com/imShakil/algos-in-py
Project-URL: Issues, https://github.com/imShakil/algos-in-py/issues
Classifier: Programming Language :: Python :: 3
Classifier: Operating System :: OS Independent
License-File: LICENSE
Dynamic: license-file
